odoo/addons/contract_sale_mandate/README.rst
odoo/addons/contract_sale_mandate/__init__.py
odoo/addons/contract_sale_mandate/__manifest__.py
odoo/addons/contract_sale_mandate/i18n/contract_sale_mandate.pot
odoo/addons/contract_sale_mandate/models/__init__.py
odoo/addons/contract_sale_mandate/models/sale_order.py
odoo/addons/contract_sale_mandate/readme/CONTRIBUTORS.rst
odoo/addons/contract_sale_mandate/readme/DESCRIPTION.rst
odoo/addons/contract_sale_mandate/static/description/icon.png
odoo/addons/contract_sale_mandate/static/description/index.html
odoo/addons/contract_sale_mandate/tests/__init__.py
odoo/addons/contract_sale_mandate/tests/test_contract_sale_mandate.py
odoo12_addon_contract_sale_mandate-12.0.2.0.0.dist-info/METADATA
odoo12_addon_contract_sale_mandate-12.0.2.0.0.dist-info/WHEEL
odoo12_addon_contract_sale_mandate-12.0.2.0.0.dist-info/top_level.txt
odoo12_addon_contract_sale_mandate-12.0.2.0.0.dist-info/RECORD
