Metadata-Version: 2.1
Name: odoo12-addon-contract-sale-mandate
Version: 12.0.2.0.0
Summary: This module manages the banking mandate from the sale order to the contract.
Home-page: https://github.com/OCA/contract
Author: ACSONE SA/NV,Odoo Community Association (OCA)
Author-email: support@odoo-community.org
License: AGPL-3
Platform: UNKNOWN
Classifier: Programming Language :: Python
Classifier: Framework :: Odoo
Classifier: License :: OSI Approved :: GNU Affero General Public License v3
Requires-Python: >=3.5
Requires-Dist: odoo12-addon-account-banking-mandate
Requires-Dist: odoo12-addon-account-banking-mandate-sale
Requires-Dist: odoo12-addon-contract
Requires-Dist: odoo12-addon-contract-mandate
Requires-Dist: odoo12-addon-product-contract
Requires-Dist: odoo (<12.1dev,>=12.0a)
